daisy_cli/__init__.py
daisy_cli/cli.py
daisy_cli/formatter.py
daisy_cli/platforms/__init__.py
daisy_cli/platforms/codeforces.py
daisy_cli/platforms/dmoj.py
daisy_cli/platforms/leetcode.py
daisy_cli/templates/dmoj/Cargo.toml.j2
daisy_cli/templates/dmoj/cli.rs.j2
daisy_cli/templates/dmoj/main.rs.j2
daisy_cli/templates/leetcode/Cargo.toml.j2
daisy_cli/templates/leetcode/lib.rs.j2
daisy_cli/utils.py
daisy_cli/writer.py
daisy_cli-0.6.5.dist-info/WHEEL
daisy_cli-0.6.5.dist-info/entry_points.txt
daisy_cli-0.6.5.dist-info/METADATA
daisy_cli-0.6.5.dist-info/RECORD
