Metadata-Version: 2.3
Name: daisy-cli
Version: 0.6.5
Summary: A Python CLI that scrapes coding sites to craft Rust problem templates.
Author: Francesco Franco
Author-email: Francesco Franco <ffrancoa97@gmail.com>
License: MIT License
Classifier: Programming Language :: Python :: 3
Classifier: Operating System :: OS Independent
Requires-Dist: beautifulsoup4>=4.13.4
Requires-Dist: jinja2>=3.1.6
Requires-Dist: lxml>=6.0.0
Requires-Dist: requests>=2.32.4
Requires-Dist: rich-click>=1.8.9
Requires-Dist: click>=8.1,<8.2
Requires-Python: >=3.13
